pytest_data_extractor/__init__.py
pytest_data_extractor/data_containers.py
pytest_data_extractor/data_storers.py
pytest_data_extractor/output_generators.py
pytest_data_extractor/pytest_extractor.py
pytest_data_extractor/utils.py
pytest_data_extractor-0.1.7.dist-info/LICENSE
pytest_data_extractor-0.1.7.dist-info/METADATA
pytest_data_extractor-0.1.7.dist-info/WHEEL
pytest_data_extractor-0.1.7.dist-info/entry_points.txt
pytest_data_extractor-0.1.7.dist-info/top_level.txt
pytest_data_extractor-0.1.7.dist-info/RECORD
