Metadata-Version: 2.1
Name: pytest-data-extractor
Version: 0.1.7
Summary: A pytest plugin to extract relevant metadata about tests into an external file (currently only json support)
Author: Maxim Mushizky
Author-email: maximmu87@gmail.com
Maintainer: Maxim Mushizky
License: MIT
Classifier: Framework :: Pytest
Classifier: Operating System :: Microsoft :: Windows
Classifier: License :: OSI Approved :: MIT License
Classifier: Programming Language :: Python :: 3
License-File: LICENSE
Requires-Dist: pytest (>=7.0.1)
Requires-Dist: setuptools (>=41.2.0)
